checkspot/__init__.py
checkspot/__main__.py
checkspot/checkspot.py
spotcheck/__init__.py
spotcheck/__main__.py
spotcheck/spotcheck.py
spotcheck-1.0.1.dist-info/DESCRIPTION.rst
spotcheck-1.0.1.dist-info/METADATA
spotcheck-1.0.1.dist-info/RECORD
spotcheck-1.0.1.dist-info/WHEEL
spotcheck-1.0.1.dist-info/entry_points.txt
spotcheck-1.0.1.dist-info/metadata.json
spotcheck-1.0.1.dist-info/top_level.txt
